chytorch/nn/__init__.py
chytorch/nn/lora/__init__.py
chytorch/nn/lora/embedding.py
chytorch/nn/lora/linear.py
chytorch/nn/losses.py
chytorch/nn/molecule/__init__.py
chytorch/nn/molecule/_embedding.py
chytorch/nn/molecule/encoder.py
chytorch/nn/reaction/__init__.py
chytorch/nn/reaction/encoder.py
chytorch/nn/slicer.py
chytorch/nn/transformer/__init__.py
chytorch/nn/transformer/attention/__init__.py
chytorch/nn/transformer/attention/graphormer.py
chytorch/nn/transformer/encoder.py
chytorch/nn/voting/__init__.py
chytorch/nn/voting/_kfold.py
chytorch/nn/voting/binary.py
chytorch/nn/voting/classifier.py
chytorch/nn/voting/regressor.py
chytorch/utils/__init__.py
chytorch/utils/data/__init__.py
chytorch/utils/data/_abc.py
chytorch/utils/data/_utils.py
chytorch/utils/data/lmdb.py
chytorch/utils/data/molecule/__init__.py
chytorch/utils/data/molecule/_unpack.cp39-win_amd64.pyd
chytorch/utils/data/molecule/_unpack.pyx
chytorch/utils/data/molecule/conformer.py
chytorch/utils/data/molecule/dummy.py
chytorch/utils/data/molecule/encoder.py
chytorch/utils/data/molecule/rdkit.py
chytorch/utils/data/product.py
chytorch/utils/data/reaction/__init__.py
chytorch/utils/data/reaction/encoder.py
chytorch/utils/data/sampler.py
chytorch/utils/data/smiles.py
chytorch/utils/data/unpack.py
chytorch/zoo/README.md
chytorch-1.65.dist-info/LICENSE
chytorch-1.65.dist-info/METADATA
chytorch-1.65.dist-info/WHEEL
chytorch-1.65.dist-info/RECORD
