Metadata-Version: 2.1
Name: chytorch
Version: 1.65
Summary: Library for modeling molecules and reactions in torch way
Home-page: https://github.com/chython/chytorch
License: MIT
Author: Ramil Nugmanov
Author-email: nougmanoff@protonmail.com
Requires-Python: >=3.8,<3.12
Classifier: Environment :: Plugins
Classifier: Intended Audience :: Science/Research
Classifier: License :: OSI Approved :: MIT License
Classifier: Operating System :: OS Independent
Classifier: Programming Language :: Python
Classifier: Programming Language :: Python :: 3
Classifier: Programming Language :: Python :: 3.8
Classifier: Programming Language :: Python :: 3.9
Classifier: Programming Language :: Python :: 3.10
Classifier: Programming Language :: Python :: 3.11
Classifier: Programming Language :: Python :: 3 :: Only
Classifier: Topic :: Scientific/Engineering
Classifier: Topic :: Scientific/Engineering :: Chemistry
Classifier: Topic :: Scientific/Engineering :: Information Analysis
Classifier: Topic :: Software Development
Classifier: Topic :: Software Development :: Libraries
Classifier: Topic :: Software Development :: Libraries :: Python Modules
Provides-Extra: lmdb
Provides-Extra: postgres
Provides-Extra: rdkit
Provides-Extra: zstd
Requires-Dist: chython (>=1.70,<2.0)
Requires-Dist: lmdb (>=1.4.1,<2.0.0) ; extra == "lmdb"
Requires-Dist: psycopg2-binary (>=2.9,<3.0) ; extra == "postgres"
Requires-Dist: pyzstd (>=0.15.9,<0.16.0) ; extra == "zstd"
Requires-Dist: rdkit (>=2023.9.1,<2024.0.0) ; extra == "rdkit"
Requires-Dist: scipy (>=1.10,<2.0)
Requires-Dist: torch (>=1.8)
Requires-Dist: torchtyping (>=0.1.4,<0.2.0)
